circuiteasy/__init__.py
circuiteasy/ac.py
circuiteasy/bjt.py
circuiteasy/complex_utils.py
circuiteasy/dc.py
circuiteasy/filter_analysis.py
circuiteasy/laplace.py
circuiteasy/power.py
circuiteasy/signal_utils.py
circuiteasy/solver.py
circuiteasy-1.0.8.dist-info/licenses/LICENSE
circuiteasy-1.0.8.dist-info/METADATA
circuiteasy-1.0.8.dist-info/WHEEL
circuiteasy-1.0.8.dist-info/top_level.txt
circuiteasy-1.0.8.dist-info/RECORD
